core_utils/__init__.py
core_utils/archives.py
core_utils/collections.py
core_utils/common.py
core_utils/env.py
core_utils/format.py
core_utils/io_utils.py
core_utils/loggers.py
core_utils/schema.py
core_utils/serialization.py
core_utils/timing.py
core_utils/url_bucket_kv.py
pywise-0.8.1.dist-info/LICENSE
pywise-0.8.1.dist-info/METADATA
pywise-0.8.1.dist-info/WHEEL
pywise-0.8.1.dist-info/RECORD
