Metadata-Version: 2.1
Name: pywise
Version: 0.8.1
Summary: Robust serialization support for NamedTuple & @DataClass data types. Various utilities and Quality-of-Life helpers. Python 3.8+ dependency only.
Home-page: https://github.com/malcolmgreaves/pywise
License: L-GPL 3.0
Author: Malcolm Greaves
Author-email: greaves.malcolm@gmail.com
Requires-Python: >=3.8.1,<4.0.0
Classifier: License :: Other/Proprietary License
Classifier: Programming Language :: Python :: 3
Classifier: Programming Language :: Python :: 3.9
Classifier: Programming Language :: Python :: 3.10
Classifier: Programming Language :: Python :: 3.11
Classifier: Programming Language :: Python :: 3.12
